{
  "default-tenant": [
    {
      "id": "f1edccaf-5829-4c8b-ac51-82dcf1aa09eb",
      "userDescription": "anything related to last week tonight show",
      "aiSummary": "This rule will block any YouTube videos related to the 'Last Week Tonight' show, including clips, segments, or full episodes.\n\n- Last Week Tonight with John Oliver\n- Last Week Tonight segments\n- Last Week Tonight clips\n- Last Week Tonight episodes\n- John Oliver Last Week Tonight\n- Last Week Tonight related videos",
      "patterns": [],
      "schedule": {
        "type": "duration",
        "durationMinutes": 60,
        "startTime": 1776623865598,
        "daysOfWeek": null,
        "endTime": null
      },
      "enabled": true,
      "createdAt": 1776623884243
    }
  ]
}